src/Dff_neg.v
module Dff_neg(clk,reset,d,q,qbar);
    input clk,reset,d;
    output reg q,qbar;

    always @(negedge clk or posedge reset) begin
        if (reset) begin
            q<=0;
            qbar<=1;
        end
        else begin
            q<= d;
            qbar<=~d;
        end
    end
endmodule

src/Dff_pos.v
module Dff_pos(clk,reset,d,q);
    input clk,reset,d;
    output reg q;

    always @(posedge clk or posedge reset) begin
        if (reset) begin
            q<=0;
        end
        else begin
            q<= d;
        end
    end
endmodule

src/clock_divider.v
module clock_divider(clk_in,reset,clk_out);
    input clk_in, reset;
    output reg clk_out;

    reg [1:0] count;

    always @(posedge clk_in or posedge reset) begin
        if (reset) begin
            clk_out<=1'b0;
            count<=2'b00;
        end
        else begin
            count <= count+1;
            if (count==2'b11) begin
                clk_out<= ~clk_out; //Output toggles after eevery 4th cycle (100 MHz---> 25 MHz)
            end
        end
    end
endmodule

src/Glitch_Free_clock_mux.v
module clock_mux(clk_100,reset,opcode,clk_out);
    input clk_100,reset;
    input [2:0] opcode;
    output wire clk_out;

    wire [3:0] a,d;
    wire sel_n;
    wire dbar1,dbar3; //qbar of FFs

    wire clk_25;
    wire sel;

    assign sel=(opcode==3'b100)?1:0; //opcode sel bit logic
    assign sel_n=~sel;

    //clock divider
    clock_divider C1(clk_100,reset,clk_25);

    //Faster Clock
    and A11(a[0],sel,dbar3);
    Dff_pos D11(clk_100,reset,a[0],d[0]);
    Dff_neg D12(clk_100,reset,d[0],d[1],dbar1);
    and A12(a[1],d[1],clk_100);

    //Slower clock
    and A21(a[2],sel_n,dbar1);
    Dff_pos D21(clk_25,reset,a[2],d[2]);
    Dff_neg D22(clk_25,reset,d[2],d[3],dbar3);
    and A22(a[3],d[3],clk_25);

    //Final output
    or Or1(clk_out,a[1],a[3]);
endmodule

src/mux_tb.v
module mux_tb;
    reg clk_in, reset;
    reg [2:0] opcode;
    wire clk_out;

    clock_mux B1(clk_in,reset,opcode,clk_out);

    initial clk_in=0;
    always #5 clk_in= ~clk_in;

    initial begin
        $dumpfile("Clock_mux.vcd");
        $dumpvars(0, mux_tb);
        reset=1;
        opcode=000; //ADD instruction
        #6 reset=0;
        #4;#250;
        opcode=100; //MUL Instruction
        #10;#500;
        opcode=001; //SUB Instruction
        #10;#2000 $finish;
    end
endmodule

src/Clock_mux.vcd
$date
	Tue Oct 21 11:37:57 2025
$end
$version
	Icarus Verilog
$end
$timescale
	1s
$end
$scope module mux_tb $end
$var wire 1 ! clk_out $end
$var reg 1 " clk_in $end
$var reg 3 # opcode [2:0] $end
$var reg 1 $ reset $end
$scope module B1 $end
$var wire 1 " clk_100 $end
$var wire 1 ! clk_out $end
$var wire 3 % opcode [2:0] $end
$var wire 1 $ reset $end
$var wire 1 & sel_n $end
$var wire 1 ' sel $end
$var wire 1 ( dbar3 $end
$var wire 1 ) dbar1 $end
$var wire 4 * d [3:0] $end
$var wire 1 + clk_25 $end
$var wire 4 , a [3:0] $end
$scope module C1 $end
$var wire 1 " clk_in $end
$var wire 1 $ reset $end
$var reg 1 + clk_out $end
$var reg 2 - count [1:0] $end
$upscope $end
$scope module D11 $end
$var wire 1 " clk $end
$var wire 1 . d $end
$var wire 1 $ reset $end
$var reg 1 / q $end
$upscope $end
$scope module D12 $end
$var wire 1 " clk $end
$var wire 1 0 d $end
$var wire 1 $ reset $end
$var reg 1 1 q $end
$var reg 1 ) qbar $end
$upscope $end
$scope module D21 $end
$var wire 1 + clk $end
$var wire 1 2 d $end
$var wire 1 $ reset $end
$var reg 1 3 q $end
$upscope $end
$scope module D22 $end
$var wire 1 + clk $end
$var wire 1 4 d $end
$var wire 1 $ reset $end
$var reg 1 5 q $end
$var reg 1 ( qbar $end
$upscope $end
$upscope $end
$upscope $end
$enddefinitions $end
$comment Show the parameter values. $end
$dumpall
$end
#0
$dumpvars
05
04
03
12
01
00
0/
0.
b0 -
b100 ,
0+
b0 *
1)
1(
0'
1&
b0 %
1$
b0 #
0"
0!
$end
#5
1"
#6
0$
#10
0"
#15
b1 -
1"
#20
0"
#25
b10 -
1"
#30
0"
#35
b11 -
1"
#40
0"
#45
14
b100 *
13
1+
b0 -
1"
#50
0"
#55
b1 -
1"
#60
0"
#65
b10 -
1"
#70
0"
#75
b11 -
1"
#80
0"
#85
0(
b1100 *
15
0+
b0 -
1"
#90
0"
#95
b1 -
1"
#100
0"
#105
b10 -
1"
#110
0"
#115
b11 -
1"
#120
0"
#125
1!
b1100 ,
1+
b0 -
1"
#130
0"
#135
b1 -
1"
#140
0"
#145
b10 -
1"
#150
0"
#155
b11 -
1"
#160
0"
#165
0!
b100 ,
0+
b0 -
1"
#170
0"
#175
b1 -
1"
#180
0"
#185
b10 -
1"
#190
0"
#195
b11 -
1"
#200
0"
#205
1!
b1100 ,
1+
b0 -
1"
#210
0"
#215
b1 -
1"
#220
0"
#225
b10 -
1"
#230
0"
#235
b11 -
1"
#240
0"
#245
0!
b100 ,
0+
b0 -
1"
#250
0"
#255
b1 -
1"
#260
02
b0 ,
0&
1'
0"
b100 #
b100 %
#265
b10 -
1"
#270
0"
#275
b11 -
1"
#280
0"
#285
04
b1000 *
03
1!
b1000 ,
1+
b0 -
1"
#290
0"
#295
b1 -
1"
#300
0"
#305
b10 -
1"
#310
0"
#315
b11 -
1"
#320
0"
#325
1.
1(
b0 *
05
0!
b1 ,
0+
b0 -
1"
#330
0"
#335
10
b1 -
b1 *
1/
1"
#340
0)
b11 *
11
0"
#345
b10 -
1!
b11 ,
1"
#350
0!
b1 ,
0"
#355
b11 -
1!
b11 ,
1"
#360
0!
b1 ,
0"
#365
1+
b0 -
1!
b11 ,
1"
#370
0!
b1 ,
0"
#375
b1 -
1!
b11 ,
1"
#380
0!
b1 ,
0"
#385
b10 -
1!
b11 ,
1"
#390
0!
b1 ,
0"
#395
b11 -
1!
b11 ,
1"
#400
0!
b1 ,
0"
#405
0+
b0 -
1!
b11 ,
1"
#410
0!
b1 ,
0"
#415
b1 -
1!
b11 ,
1"
#420
0!
b1 ,
0"
#425
b10 -
1!
b11 ,
1"
#430
0!
b1 ,
0"
#435
b11 -
1!
b11 ,
1"
#440
0!
b1 ,
0"
#445
1+
b0 -
1!
b11 ,
1"
#450
0!
b1 ,
0"
#455
b1 -
1!
b11 ,
1"
#460
0!
b1 ,
0"
#465
b10 -
1!
b11 ,
1"
#470
0!
b1 ,
0"
#475
b11 -
1!
b11 ,
1"
#480
0!
b1 ,
0"
#485
0+
b0 -
1!
b11 ,
1"
#490
0!
b1 ,
0"
#495
b1 -
1!
b11 ,
1"
#500
0!
b1 ,
0"
#505
b10 -
1!
b11 ,
1"
#510
0!
b1 ,
0"
#515
b11 -
1!
b11 ,
1"
#520
0!
b1 ,
0"
#525
1+
b0 -
1!
b11 ,
1"
#530
0!
b1 ,
0"
#535
b1 -
1!
b11 ,
1"
#540
0!
b1 ,
0"
#545
b10 -
1!
b11 ,
1"
#550
0!
b1 ,
0"
#555
b11 -
1!
b11 ,
1"
#560
0!
b1 ,
0"
#565
0+
b0 -
1!
b11 ,
1"
#570
0!
b1 ,
0"
#575
b1 -
1!
b11 ,
1"
#580
0!
b1 ,
0"
#585
b10 -
1!
b11 ,
1"
#590
0!
b1 ,
0"
#595
b11 -
1!
b11 ,
1"
#600
0!
b1 ,
0"
#605
1+
b0 -
1!
b11 ,
1"
#610
0!
b1 ,
0"
#615
b1 -
1!
b11 ,
1"
#620
0!
b1 ,
0"
#625
b10 -
1!
b11 ,
1"
#630
0!
b1 ,
0"
#635
b11 -
1!
b11 ,
1"
#640
0!
b1 ,
0"
#645
0+
b0 -
1!
b11 ,
1"
#650
0!
b1 ,
0"
#655
b1 -
1!
b11 ,
1"
#660
0!
b1 ,
0"
#665
b10 -
1!
b11 ,
1"
#670
0!
b1 ,
0"
#675
b11 -
1!
b11 ,
1"
#680
0!
b1 ,
0"
#685
1+
b0 -
1!
b11 ,
1"
#690
0!
b1 ,
0"
#695
b1 -
1!
b11 ,
1"
#700
0!
b1 ,
0"
#705
b10 -
1!
b11 ,
1"
#710
0!
b1 ,
0"
#715
b11 -
1!
b11 ,
1"
#720
0!
b1 ,
0"
#725
0+
b0 -
1!
b11 ,
1"
#730
0!
b1 ,
0"
#735
b1 -
1!
b11 ,
1"
#740
0!
b1 ,
0"
#745
b10 -
1!
b11 ,
1"
#750
0!
b1 ,
0"
#755
b11 -
1!
b11 ,
1"
#760
0!
b1 ,
0"
#765
1+
b0 -
1!
b11 ,
1"
#770
0.
0!
1&
0'
b0 ,
0"
b1 #
b1 %
#775
00
b1 -
b10 *
0/
1!
b10 ,
1"
#780
12
1)
b0 *
01
0!
b100 ,
0"
#785
b10 -
1"
#790
0"
#795
b11 -
1"
#800
0"
#805
0+
b0 -
1"
#810
0"
#815
b1 -
1"
#820
0"
#825
b10 -
1"
#830
0"
#835
b11 -
1"
#840
0"
#845
14
b100 *
13
1+
b0 -
1"
#850
0"
#855
b1 -
1"
#860
0"
#865
b10 -
1"
#870
0"
#875
b11 -
1"
#880
0"
#885
0(
b1100 *
15
0+
b0 -
1"
#890
0"
#895
b1 -
1"
#900
0"
#905
b10 -
1"
#910
0"
#915
b11 -
1"
#920
0"
#925
1!
b1100 ,
1+
b0 -
1"
#930
0"
#935
b1 -
1"
#940
0"
#945
b10 -
1"
#950
0"
#955
b11 -
1"
#960
0"
#965
0!
b100 ,
0+
b0 -
1"
#970
0"
#975
b1 -
1"
#980
0"
#985
b10 -
1"
#990
0"
#995
b11 -
1"
#1000
0"
#1005
1!
b1100 ,
1+
b0 -
1"
#1010
0"
#1015
b1 -
1"
#1020
0"
#1025
b10 -
1"
#1030
0"
#1035
b11 -
1"
#1040
0"
#1045
0!
b100 ,
0+
b0 -
1"
#1050
0"
#1055
b1 -
1"
#1060
0"
#1065
b10 -
1"
#1070
0"
#1075
b11 -
1"
#1080
0"
#1085
1!
b1100 ,
1+
b0 -
1"
#1090
0"
#1095
b1 -
1"
#1100
0"
#1105
b10 -
1"
#1110
0"
#1115
b11 -
1"
#1120
0"
#1125
0!
b100 ,
0+
b0 -
1"
#1130
0"
#1135
b1 -
1"
#1140
0"
#1145
b10 -
1"
#1150
0"
#1155
b11 -
1"
#1160
0"
#1165
1!
b1100 ,
1+
b0 -
1"
#1170
0"
#1175
b1 -
1"
#1180
0"
#1185
b10 -
1"
#1190
0"
#1195
b11 -
1"
#1200
0"
#1205
0!
b100 ,
0+
b0 -
1"
#1210
0"
#1215
b1 -
1"
#1220
0"
#1225
b10 -
1"
#1230
0"
#1235
b11 -
1"
#1240
0"
#1245
1!
b1100 ,
1+
b0 -
1"
#1250
0"
#1255
b1 -
1"
#1260
0"
#1265
b10 -
1"
#1270
0"
#1275
b11 -
1"
#1280
0"
#1285
0!
b100 ,
0+
b0 -
1"
#1290
0"
#1295
b1 -
1"
#1300
0"
#1305
b10 -
1"
#1310
0"
#1315
b11 -
1"
#1320
0"
#1325
1!
b1100 ,
1+
b0 -
1"
#1330
0"
#1335
b1 -
1"
#1340
0"
#1345
b10 -
1"
#1350
0"
#1355
b11 -
1"
#1360
0"
#1365
0!
b100 ,
0+
b0 -
1"
#1370
0"
#1375
b1 -
1"
#1380
0"
#1385
b10 -
1"
#1390
0"
#1395
b11 -
1"
#1400
0"
#1405
1!
b1100 ,
1+
b0 -
1"
#1410
0"
#1415
b1 -
1"
#1420
0"
#1425
b10 -
1"
#1430
0"
#1435
b11 -
1"
#1440
0"
#1445
0!
b100 ,
0+
b0 -
1"
#1450
0"
#1455
b1 -
1"
#1460
0"
#1465
b10 -
1"
#1470
0"
#1475
b11 -
1"
#1480
0"
#1485
1!
b1100 ,
1+
b0 -
1"
#1490
0"
#1495
b1 -
1"
#1500
0"
#1505
b10 -
1"
#1510
0"
#1515
b11 -
1"
#1520
0"
#1525
0!
b100 ,
0+
b0 -
1"
#1530
0"
#1535
b1 -
1"
#1540
0"
#1545
b10 -
1"
#1550
0"
#1555
b11 -
1"
#1560
0"
#1565
1!
b1100 ,
1+
b0 -
1"
#1570
0"
#1575
b1 -
1"
#1580
0"
#1585
b10 -
1"
#1590
0"
#1595
b11 -
1"
#1600
0"
#1605
0!
b100 ,
0+
b0 -
1"
#1610
0"
#1615
b1 -
1"
#1620
0"
#1625
b10 -
1"
#1630
0"
#1635
b11 -
1"
#1640
0"
#1645
1!
b1100 ,
1+
b0 -
1"
#1650
0"
#1655
b1 -
1"
#1660
0"
#1665
b10 -
1"
#1670
0"
#1675
b11 -
1"
#1680
0"
#1685
0!
b100 ,
0+
b0 -
1"
#1690
0"
#1695
b1 -
1"
#1700
0"
#1705
b10 -
1"
#1710
0"
#1715
b11 -
1"
#1720
0"
#1725
1!
b1100 ,
1+
b0 -
1"
#1730
0"
#1735
b1 -
1"
#1740
0"
#1745
b10 -
1"
#1750
0"
#1755
b11 -
1"
#1760
0"
#1765
0!
b100 ,
0+
b0 -
1"
#1770
0"
#1775
b1 -
1"
#1780
0"
#1785
b10 -
1"
#1790
0"
#1795
b11 -
1"
#1800
0"
#1805
1!
b1100 ,
1+
b0 -
1"
#1810
0"
#1815
b1 -
1"
#1820
0"
#1825
b10 -
1"
#1830
0"
#1835
b11 -
1"
#1840
0"
#1845
0!
b100 ,
0+
b0 -
1"
#1850
0"
#1855
b1 -
1"
#1860
0"
#1865
b10 -
1"
#1870
0"
#1875
b11 -
1"
#1880
0"
#1885
1!
b1100 ,
1+
b0 -
1"
#1890
0"
#1895
b1 -
1"
#1900
0"
#1905
b10 -
1"
#1910
0"
#1915
b11 -
1"
#1920
0"
#1925
0!
b100 ,
0+
b0 -
1"
#1930
0"
#1935
b1 -
1"
#1940
0"
#1945
b10 -
1"
#1950
0"
#1955
b11 -
1"
#1960
0"
#1965
1!
b1100 ,
1+
b0 -
1"
#1970
0"
#1975
b1 -
1"
#1980
0"
#1985
b10 -
1"
#1990
0"
#1995
b11 -
1"
#2000
0"
#2005
0!
b100 ,
0+
b0 -
1"
#2010
0"
#2015
b1 -
1"
#2020
0"
#2025
b10 -
1"
#2030
0"
#2035
b11 -
1"
#2040
0"
#2045
1!
b1100 ,
1+
b0 -
1"
#2050
0"
#2055
b1 -
1"
#2060
0"
#2065
b10 -
1"
#2070
0"
#2075
b11 -
1"
#2080
0"
#2085
0!
b100 ,
0+
b0 -
1"
#2090
0"
#2095
b1 -
1"
#2100
0"
#2105
b10 -
1"
#2110
0"
#2115
b11 -
1"
#2120
0"
#2125
1!
b1100 ,
1+
b0 -
1"
#2130
0"
#2135
b1 -
1"
#2140
0"
#2145
b10 -
1"
#2150
0"
#2155
b11 -
1"
#2160
0"
#2165
0!
b100 ,
0+
b0 -
1"
#2170
0"
#2175
b1 -
1"
#2180
0"
#2185
b10 -
1"
#2190
0"
#2195
b11 -
1"
#2200
0"
#2205
1!
b1100 ,
1+
b0 -
1"
#2210
0"
#2215
b1 -
1"
#2220
0"
#2225
b10 -
1"
#2230
0"
#2235
b11 -
1"
#2240
0"
#2245
0!
b100 ,
0+
b0 -
1"
#2250
0"
#2255
b1 -
1"
#2260
0"
#2265
b10 -
1"
#2270
0"
#2275
b11 -
1"
#2280
0"
#2285
1!
b1100 ,
1+
b0 -
1"
#2290
0"
#2295
b1 -
1"
#2300
0"
#2305
b10 -
1"
#2310
0"
#2315
b11 -
1"
#2320
0"
#2325
0!
b100 ,
0+
b0 -
1"
#2330
0"
#2335
b1 -
1"
#2340
0"
#2345
b10 -
1"
#2350
0"
#2355
b11 -
1"
#2360
0"
#2365
1!
b1100 ,
1+
b0 -
1"
#2370
0"
#2375
b1 -
1"
#2380
0"
#2385
b10 -
1"
#2390
0"
#2395
b11 -
1"
#2400
0"
#2405
0!
b100 ,
0+
b0 -
1"
#2410
0"
#2415
b1 -
1"
#2420
0"
#2425
b10 -
1"
#2430
0"
#2435
b11 -
1"
#2440
0"
#2445
1!
b1100 ,
1+
b0 -
1"
#2450
0"
#2455
b1 -
1"
#2460
0"
#2465
b10 -
1"
#2470
0"
#2475
b11 -
1"
#2480
0"
#2485
0!
b100 ,
0+
b0 -
1"
#2490
0"
#2495
b1 -
1"
#2500
0"
#2505
b10 -
1"
#2510
0"
#2515
b11 -
1"
#2520
0"
#2525
1!
b1100 ,
1+
b0 -
1"
#2530
0"
#2535
b1 -
1"
#2540
0"
#2545
b10 -
1"
#2550
0"
#2555
b11 -
1"
#2560
0"
#2565
0!
b100 ,
0+
b0 -
1"
#2570
0"
#2575
b1 -
1"
#2580
0"
#2585
b10 -
1"
#2590
0"
#2595
b11 -
1"
#2600
0"
#2605
1!
b1100 ,
1+
b0 -
1"
#2610
0"
#2615
b1 -
1"
#2620
0"
#2625
b10 -
1"
#2630
0"
#2635
b11 -
1"
#2640
0"
#2645
0!
b100 ,
0+
b0 -
1"
#2650
0"
#2655
b1 -
1"
#2660
0"
#2665
b10 -
1"
#2670
0"
#2675
b11 -
1"
#2680
0"
#2685
1!
b1100 ,
1+
b0 -
1"
#2690
0"
#2695
b1 -
1"
#2700
0"
#2705
b10 -
1"
#2710
0"
#2715
b11 -
1"
#2720
0"
#2725
0!
b100 ,
0+
b0 -
1"
#2730
0"
#2735
b1 -
1"
#2740
0"
#2745
b10 -
1"
#2750
0"
#2755
b11 -
1"
#2760
0"
#2765
1!
b1100 ,
1+
b0 -
1"
#2770
0"
#2775
b1 -
1"
